apitut_nirmit/apitut_nirmit.py
apitut_nirmit/apitut_nirmit2.py
apitut_nirmit/apitut_nirmit3.py
apitut_nirmit/apitut_nirmit4.py
apitut_nirmit/apitut_nirmit5.py
apitut_nirmit/apitut_nirmit6.py
apitut_nirmit/apitut_nirmit7.py
apitut_nirmit-0.7.12.dist-info/METADATA
apitut_nirmit-0.7.12.dist-info/WHEEL
apitut_nirmit-0.7.12.dist-info/top_level.txt
apitut_nirmit-0.7.12.dist-info/RECORD
