Metadata-Version: 2.1
Name: apitut-nirmit
Version: 0.7.12
Summary: A tutorial package for creating APIs
Author: Nirmit Sakre
Author-email: nirmitsakre@gmail.com
Requires-Dist: requests
Requires-Dist: flask
